Metadata-Version: 1.0
Name: wbcontroller
Version: 0.0.8
Summary: Setup básico inicial para projetos utilizando o WeBots
Home-page: UNKNOWN
Author: Miguel L. Rodrigues
Author-email: miguellukas52@gmail.com
License: MIT License
Keywords: webots basic python setup
Platform: UNKNOWN
